Arquitectura/ALU.sv
module alu (
    input logic [31:0] a, b,
    input logic [3:0] op,
    output logic [31:0] x
    );

    always @(a or b or op)
        case(op)
            4'b0000: x <= a + b;
            4'b1000: x <= a - b;
            4'b0001: x <= a << b;
            4'b0101: x <= a >> b;
            4'b1001: x <= a >>> b;
            4'b0010: x <= ($signed(a) < $signed(b));
            4'b0011: x <= a < b;
            4'b0111: x <= a & b;
            4'b0110: x <= a | b;
            4'b0100: x <= a ^ b;
            default: x <= 32'b0; // Valor por defecto si el opcode no coincide
        endcase
endmodule

Arquitectura/testbanch.sv
module tb_alu;

    // Inputs
    reg [31:0] a;
    reg [31:0] b;
    reg [3:0] op;

    // Outputs
    wire [31:0] x;

    // Instantiate the Unit Under Test (UUT)
    alu uut (
        .a(a),
        .b(b),
        .op(op),
        .x(x)
    );

    initial begin
        //vcd file
        $dumpfile("tb_alu.vcd");
        $dumpvars(0, tb_alu);

        // Initialize Inputs
        a = 32'h20;
        b = 32'h2;
        op = 4'b0000;

        #10;

        op = 4'b1000;

        #10;

        op = 4'b0001;

        #10;

        op = 4'b0101;

        #10;

        op = 4'b1101;

        #10;

        op = 4'b0010;

        #10;

        op = 4'b0011;

        #10;

        op = 4'b0111;

        #10;

        op = 4'b0110;

        #10;

        op = 4'b0100;
        
        $finish;
    end

endmodule

Arquitectura/tb_alu.vcd
$date
	Thu Aug 24 14:17:16 2023
$end
$version
	Icarus Verilog
$end
$timescale
	1s
$end
$scope module tb_alu $end
$var wire 32 ! x [31:0] $end
$var reg 32 " a [31:0] $end
$var reg 32 # b [31:0] $end
$var reg 4 $ op [3:0] $end
$scope module uut $end
$var wire 32 % a [31:0] $end
$var wire 32 & b [31:0] $end
$var wire 4 ' op [3:0] $end
$var reg 32 ( x [31:0] $end
$upscope $end
$upscope $end
$enddefinitions $end
#0
$dumpvars
b100010 (
b0 '
b10 &
b100000 %
b0 $
b10 #
b100000 "
b100010 !
$end
#10
b11110 !
b11110 (
b1000 $
b1000 '
#20
b10000000 !
b10000000 (
b1 $
b1 '
#30
b1000 !
b1000 (
b101 $
b101 '
#40
b0 !
b0 (
b1101 $
b1101 '
#50
b10 $
b10 '
#60
b11 $
b11 '
#70
b111 $
b111 '
#80
b100010 !
b100010 (
b110 $
b110 '
#90
b100 $
b100 '
