RU/ru.sv
module registersmemory (
    input [4:0] r1,
    input [4:0] r2,
    input [4:0] rd,
    input [31:0] datawrite,
    input Ruwr,
    input clk, // nueva entrada de reloj
    output reg [31:0] r1out,
    output reg [31:0] r2out
  );
  
    reg [31:0] RF [0:31];
  
    always @(negedge clk) begin // usar el flanco de subida del reloj
      if (Ruwr == 1 && r1!=0) begin
        RF[rd] <= datawrite;
      end 
      if (Ruwr==0) begin
        r1out <= RF[r1];
        r2out <= RF[r2];
      end
    end
  
    initial begin
      $readmemb("registerfile.txt", RF);
    end
    
  endmodule

RU/testbench.sv
module testbench();
    reg [4:0] r1;
    reg [4:0] r2;
    reg [4:0] rd;
    reg [31:0] datawrite;
    reg Ruwr;
    wire [31:0] r1out;
    wire [31:0] r2out;
    reg clk = 0;
  
    // Generar una señal de reloj de 50 MHz
    always #10 clk = ~clk;
  
    registersmemory rm1(r1, r2, rd, datawrite, Ruwr, clk, r1out, r2out);
  
    initial begin
      $dumpfile("dump.vcd");
      $dumpvars(1);
      // Escritura
      Ruwr = 0; r2 = 0; r1 = 1; datawrite = 0; rd = 0;
      #20;
      Ruwr = 1; datawrite = 481184; rd = 0;
      #20;
      Ruwr = 0; r2 = 0; r1 = 1; datawrite = 0; rd = 0;
      #20;
      // Escritura
      Ruwr = 1; datawrite = 572264; rd = 0;
      #20;
      Ruwr = 0; r2 = 0; r1 = 1; datawrite = 0; rd = 0;
      #20;
      // Escritura
      Ruwr = 1; datawrite = 342916; rd = 0;
      #20;
      Ruwr = 0; r2 = 0; r1 = 1; datawrite = 0; rd = 0;
      #20;
      // Escritura
      Ruwr = 1; datawrite = 1234673; rd = 0;
      #20;
      Ruwr = 0; r2 = 0; r1 = 1; datawrite = 0; rd = 0;
      #20;
  
      $finish();
    end
  endmodule

RU/dump.vcd
$date
	Sat Feb 24 16:03:59 2024
$end
$version
	Icarus Verilog
$end
$timescale
	1s
$end
$scope module testbench $end
$var wire 32 ! r2out [31:0] $end
$var wire 32 " r1out [31:0] $end
$var reg 1 # Ruwr $end
$var reg 1 $ clk $end
$var reg 32 % datawrite [31:0] $end
$var reg 5 & r1 [4:0] $end
$var reg 5 ' r2 [4:0] $end
$var reg 5 ( rd [4:0] $end
$upscope $end
$enddefinitions $end
#0
$dumpvars
b0 (
b0 '
b1 &
b0 %
0$
0#
b11111111111111111111111111111111 "
b0 !
$end
#10
1$
#20
0$
b1110101011110100000 %
1#
#30
1$
#40
b1110101011110100000 !
0$
b0 %
0#
#50
1$
#60
0$
b10001011101101101000 %
1#
#70
1$
#80
b10001011101101101000 !
0$
b0 %
0#
#90
1$
#100
0$
b1010011101110000100 %
1#
#110
1$
#120
b1010011101110000100 !
0$
b0 %
0#
#130
1$
#140
0$
b100101101011011110001 %
1#
#150
1$
#160
b100101101011011110001 !
0$
b0 %
0#
